icolos/__init__.py
icolos/__pycache__/__init__.cpython-39.pyc
icolos/config/schemas/schemas.py
icolos/config_containers/__init__.py
icolos/config_containers/container.py
icolos/config_containers/workflow_container.py
icolos/core/__init__.py
icolos/core/steps_utils.py
icolos/core/__pycache__/__init__.cpython-39.pyc
icolos/core/composite_agents/__init__.py
icolos/core/composite_agents/base_agent.py
icolos/core/composite_agents/scheduler.py
icolos/core/composite_agents/workflow.py
icolos/core/composite_agents/__pycache__/__init__.cpython-39.pyc
icolos/core/composite_agents/__pycache__/workflow.cpython-39.pyc
icolos/core/containers/__init__.py
icolos/core/containers/compound.py
icolos/core/containers/generic.py
icolos/core/containers/gmx_state.py
icolos/core/containers/gromacs_topol.py
icolos/core/containers/perturbation_map.py
icolos/core/flow_control/__init__.py
icolos/core/flow_control/flow_control.py
icolos/core/flow_control/iterator.py
icolos/core/step_dispatch/__init__.py
icolos/core/step_dispatch/dispatcher.py
icolos/core/step_utils/__init__.py
icolos/core/step_utils/gold_config.py
icolos/core/step_utils/input_merger.py
icolos/core/step_utils/input_preparator.py
icolos/core/step_utils/obabel_structconvert.py
icolos/core/step_utils/rdkit_utils.py
icolos/core/step_utils/retry.py
icolos/core/step_utils/run_variables_resolver.py
icolos/core/step_utils/sdconvert_util.py
icolos/core/step_utils/step_writeout.py
icolos/core/step_utils/structcat_util.py
icolos/core/step_utils/structconvert.py
icolos/core/workflow_steps/__init__.py
icolos/core/workflow_steps/step.py
icolos/core/workflow_steps/active_learning/__init__.py
icolos/core/workflow_steps/active_learning/acquisition_function.py
icolos/core/workflow_steps/active_learning/active_learning_vl_screen.py
icolos/core/workflow_steps/active_learning/al_utils.py
icolos/core/workflow_steps/active_learning/base.py
icolos/core/workflow_steps/active_learning/learner.py
icolos-1.10.0.dist-info/LICENCE
icolos-1.10.0.dist-info/METADATA
icolos-1.10.0.dist-info/WHEEL
icolos-1.10.0.dist-info/entry_points.txt
icolos-1.10.0.dist-info/top_level.txt
icolos-1.10.0.dist-info/RECORD
