Metadata-Version: 2.1
Name: icolos
Version: 1.10.0
Summary: Icolos Workflow Manager
Home-page: https://github.com/MolecularAI/Icolos
Maintainer: Christian Margreitter, Harry Moore
License: UNKNOWN
Platform: UNKNOWN
Requires-Python: >=3.8
License-File: LICENCE
